Workbook

Sheet Read me
A1: Rogue Deck – LiveOps Economy Model
A2: Design exercise for markherdt.dev. All values are assumptions unless noted.
A4: How to use
A5: Blue cells on a yellow background are inputs. Change them and every other sheet recalculates.
A6: Black cells are formulas. Green cells pull values from another sheet.
A8: Sheets
A9: Assumptions | B9: Economy parameters: rewards, caps, prices.
A10: Profiles | B10: Monthly gold and pack income per player profile (free and paying).
A11: Monetization | B11: Gem bundles, price per pack, and offer value.
A12: Pack Odds | B12: Rarity and art-tier odds per card and per pack.
A13: Crafting | B13: Dismantle and craft values per rarity.
A14: Collection Sim | B14: Monte Carlo output (Python, 300 runs): collection progress per profile over 6 months. Static values.
A16: Sources
A17: Match length (15 min), rarity weights 8/4/2/1, effect counts (35 card variants, 26 Rogue variants): Rogue Deck game data / designer.
A18: Free-pack target of 1–2 per day (~30/month): designer target.

Sheet Assumptions
A1: Parameter | B1: Value | C1: Unit | D1: Note
A2: Match length | B2: 15 | C2: min | D2: Designer estimate, 2–4 players
A3: Win rate | B3: 0.5 | C3: % | D3: Matchmaking target
A4: Gold per win | B4: 10 | C4: gold
A5: Gold per loss | B5: 4 | C5: gold | D5: Small reward so losing still progresses
A6: Daily cap on match gold | B6: 30 | C6: gold/day | D6: Anti-botting; keeps quests and gems relevant
A7: Daily quests required | B7: 3 | C7: quests | D7: 5 offered, 3 required
A8: Gold per daily quest | B8: 10 | C8: gold
A9: Bonus for all 5 daily quests | B9: 10 | C9: gold | D9: Bonus, not the main reward
A10: Weekly quests required | B10: 4 | C10: quests | D10: 6 offered, 4 required
A11: Gold per weekly quest | B11: 15 | C11: gold
A12: Packs for finishing the weekly | B12: 1 | C12: packs
A13: Monthly quests required | B13: 5 | C13: quests | D13: 8 offered, 5 required
A14: Gold per monthly quest | B14: 25 | C14: gold
A15: Packs for finishing the monthly | B15: 2 | C15: packs | D15: Plus 1 art-upgrade token
A16: Season pass: free-track packs | B16: 3 | C16: packs/season | D16: Season = 4 weeks
A17: Season pass: premium-track packs | B17: 12 | C17: packs/season | D17: In addition to the free track
A18: Pack price in gold | B18: 150 | C18: gold
A19: Daily free pack (easy objective) | B19: 1 | C19: packs/day | D19: "Play 1 match"
A20: Daily Pack Pass: packs per day | B20: 1 | C20: packs/day | D20: Deferred: 1 pack per day for 30 days
A21: Daily Pack Pass: length | B21: 30 | C21: days
A22: Weeks per month | B22: 4 | C22: weeks | D22: Simplification

Sheet Profiles
A1: Inputs (per month) | B1: Casual | C1: Regular | D1: Engaged | E1: Hardcore
A2: Active days | B2: 10 | C2: 18 | D2: 26 | E2: 30
A3: Matches per active day | B3: 2 | C3: 3 | D3: 6 | E3: 12
A4: Daily quests done per active day | B4: 2 | C4: 3 | D4: 3 | E4: 3
A5: Share of all-5 daily bonuses | B5: 0 | C5: 0.2 | D5: 0.6 | E5: 1
A6: Weeklies completed (share) | B6: 0.25 | C6: 0.75 | D6: 1 | E6: 1
A7: Monthly completed (0/1) | B7: 0 | C7: 0 | D7: 1 | E7: 1
A8: Season pass free track reached (share) | B8: 0.4 | C8: 0.75 | D8: 1 | E8: 1
A10: Outputs (per month) | B10: Casual | C10: Regular | D10: Engaged | E10: Hardcore
A11: Hours played | B11: =B2*B3*Assumptions!$B$2/60 -> 5 | C11: =C2*C3*Assumptions!$B$2/60 -> 13.5 | D11: =D2*D3*Assumptions!$B$2/60 -> 39 | E11: =E2*E3*Assumptions!$B$2/60 -> 90
A12: Avg gold per match | B12: =Assumptions!$B$3*Assumptions!$B$4+(1-Assumptions!$B$3)*Assumptions!$B$5 -> 7 | C12: =Assumptions!$B$3*Assumptions!$B$4+(1-Assumptions!$B$3)*Assumptions!$B$5 -> 7 | D12: =Assumptions!$B$3*Assumptions!$B$4+(1-Assumptions!$B$3)*Assumptions!$B$5 -> 7 | E12: =Assumptions!$B$3*Assumptions!$B$4+(1-Assumptions!$B$3)*Assumptions!$B$5 -> 7
A13: Match gold per active day (capped) | B13: =MIN(B3*B12,Assumptions!$B$6) -> 14 | C13: =MIN(C3*C12,Assumptions!$B$6) -> 21 | D13: =MIN(D3*D12,Assumptions!$B$6) -> 30 | E13: =MIN(E3*E12,Assumptions!$B$6) -> 30
A14: Match gold | B14: =B2*B13 -> 140 | C14: =C2*C13 -> 378 | D14: =D2*D13 -> 780 | E14: =E2*E13 -> 900
A15: Daily quest gold | B15: =B2*(MIN(B4,Assumptions!$B$7)*Assumptions!$B$8+B5*Assumptions!$B$9) -> 200 | C15: =C2*(MIN(C4,Assumptions!$B$7)*Assumptions!$B$8+C5*Assumptions!$B$9) -> 576 | D15: =D2*(MIN(D4,Assumptions!$B$7)*Assumptions!$B$8+D5*Assumptions!$B$9) -> 936 | E15: =E2*(MIN(E4,Assumptions!$B$7)*Assumptions!$B$8+E5*Assumptions!$B$9) -> 1200
A16: Weekly + monthly quest gold | B16: =Assumptions!$B$22*B6*Assumptions!$B$10*Assumptions!$B$11+B7*Assumptions!$B$13*Assumptions!$B$14 -> 60 | C16: =Assumptions!$B$22*C6*Assumptions!$B$10*Assumptions!$B$11+C7*Assumptions!$B$13*Assumptions!$B$14 -> 180 | D16: =Assumptions!$B$22*D6*Assumptions!$B$10*Assumptions!$B$11+D7*Assumptions!$B$13*Assumptions!$B$14 -> 365 | E16: =Assumptions!$B$22*E6*Assumptions!$B$10*Assumptions!$B$11+E7*Assumptions!$B$13*Assumptions!$B$14 -> 365
A17: Total gold | B17: =B14+B15+B16 -> 400 | C17: =C14+C15+C16 -> 1134 | D17: =D14+D15+D16 -> 2081 | E17: =E14+E15+E16 -> 2465
A18: Packs bought with gold | B18: =B17/Assumptions!$B$18 -> 2.6666667 | C18: =C17/Assumptions!$B$18 -> 7.56 | D18: =D17/Assumptions!$B$18 -> 13.873333 | E18: =E17/Assumptions!$B$18 -> 16.433333
A19: Daily free packs | B19: =B2*Assumptions!$B$19 -> 10 | C19: =C2*Assumptions!$B$19 -> 18 | D19: =D2*Assumptions!$B$19 -> 26 | E19: =E2*Assumptions!$B$19 -> 30
A20: Reward packs (weekly, monthly, free pass) | B20: =Assumptions!$B$22*B6*Assumptions!$B$12+B7*Assumptions!$B$15+B8*Assumptions!$B$16 -> 2.2 | C20: =Assumptions!$B$22*C6*Assumptions!$B$12+C7*Assumptions!$B$15+C8*Assumptions!$B$16 -> 5.25 | D20: =Assumptions!$B$22*D6*Assumptions!$B$12+D7*Assumptions!$B$15+D8*Assumptions!$B$16 -> 9 | E20: =Assumptions!$B$22*E6*Assumptions!$B$12+E7*Assumptions!$B$15+E8*Assumptions!$B$16 -> 9
A21: FREE PACKS PER MONTH | B21: =B18+B19+B20 -> 14.866667 | C21: =C18+C19+C20 -> 30.81 | D21: =D18+D19+D20 -> 48.873333 | E21: =E18+E19+E20 -> 55.433333
A22: Free packs per active day | B22: =IF(B2>0,B21/B2,0) -> 1.4866667 | C22: =IF(C2>0,C21/C2,0) -> 1.7116667 | D22: =IF(D2>0,D21/D2,0) -> 1.8797436 | E22: =IF(E2>0,E21/E2,0) -> 1.8477778
A23: Paying player: + premium pass packs | B23: =B21+Assumptions!$B$17 -> 26.866667 | C23: =C21+Assumptions!$B$17 -> 42.81 | D23: =D21+Assumptions!$B$17 -> 60.873333 | E23: =E21+Assumptions!$B$17 -> 67.433333
A24: Paying player: + Daily Pack Pass | B24: =B23+Assumptions!$B$20*Assumptions!$B$21 -> 56.866667 | C24: =C23+Assumptions!$B$20*Assumptions!$B$21 -> 72.81 | D24: =D23+Assumptions!$B$20*Assumptions!$B$21 -> 90.873333 | E24: =E23+Assumptions!$B$20*Assumptions!$B$21 -> 97.433333

Sheet Monetization
A1: Gem bundle | B1: Price (€) | C1: Gems | D1: Bonus vs. base | E1: Packs (at 100 gems) | F1: € per pack | H1: Pack price in gems | I1: 100
A2: Small | B2: 4.99 | C2: 500 | D2: =C2/(B2/$B$2*$C$2)-1 -> 0 | E2: =C2/$I$1 -> 5 | F2: =B2/E2 -> 0.998
A3: Medium | B3: 9.99 | C3: 1100 | D3: =C3/(B3/$B$2*$C$2)-1 -> 0.098898899 | E3: =C3/$I$1 -> 11 | F3: =B3/E3 -> 0.90818182
A4: Large | B4: 19.99 | C4: 2400 | D4: =C4/(B4/$B$2*$C$2)-1 -> 0.1981991 | E4: =C4/$I$1 -> 24 | F4: =B4/E4 -> 0.83291667
A5: Huge | B5: 49.99 | C5: 6500 | D5: =C5/(B5/$B$2*$C$2)-1 -> 0.29765953 | E5: =C5/$I$1 -> 65 | F5: =B5/E5 -> 0.76907692
A7: Offer | B7: Price (€) | C7: Packs | D7: Other contents | E7: € per pack | F7: Discount vs. Small bundle
A8: Daily Pack Pass (1 pack/day, 30 days) | B8: 4.99 | C8: =Assumptions!$B$20*Assumptions!$B$21 -> 30 | D8: Deferred: must log in on 30 days | E8: =B8/C8 -> 0.16633333 | F8: =1-E8/$F$2 -> 0.83333333
A9: Season pass – premium track | B9: 9.99 | C9: =Assumptions!$B$17 -> 12 | D9: 2 art-upgrade tokens, cosmetics | E9: =B9/C9 -> 0.8325 | F9: =1-E9/$F$2 -> 0.16583166
A10: Starter deck (fixed cards, default art) | B10: 4.99 | C10: 10 | D10: 52 fixed cards ≈ 10 packs worth, no randomness | E10: =B10/C10 -> 0.499 | F10: =1-E10/$F$2 -> 0.5
A11: Launch bundle (limited) | B11: 9.99 | C11: 15 | D11: Card back, 500 crafting materials | E11: =B11/C11 -> 0.666 | F11: =1-E11/$F$2 -> 0.33266533
A13: Starter deck "packs" = 52 cards / 5 cards per pack, rounded. Prices are assumptions for a mid-range F2P card game.

Sheet Pack Odds
A1: Rarity | B1: Weight | C1: Chance per card | D1: Card-effect variants | E1: Rogue variants
A2: Common | B2: 8 | C2: =B2/SUM($B$2:$B$5) -> 0.53333333 | D2: 9 | E2: 4
A3: Rare | B3: 4 | C3: =B3/SUM($B$2:$B$5) -> 0.26666667 | D3: 8 | E3: 6
A4: Epic | B4: 2 | C4: =B4/SUM($B$2:$B$5) -> 0.13333333 | D4: 10 | E4: 7
A5: Legendary | B5: 1 | C5: =B5/SUM($B$2:$B$5) -> 0.066666667 | D5: 8 | E5: 9
A6: Total | D6: =SUM(D2:D5) -> 35 | E6: =SUM(E2:E5) -> 26
A7: Weights 8/4/2/1 are the same as the in-match Rogue offers.
A9: Art tier | B9: Weight | C9: Chance per card | D9: Expected per pack | E9: Packs per one copy | G9: Cards per pack | H9: 5
A10: Default | B10: 80 | C10: =B10/SUM($B$10:$B$13) -> 0.8 | D10: =C10*$H$9 -> 4 | E10: =1/D10 -> 0.25
A11: Holo | B11: 14 | C11: =B11/SUM($B$10:$B$13) -> 0.14 | D11: =C11*$H$9 -> 0.7 | E11: =1/D11 -> 1.4285714
A12: Full Art | B12: 5 | C12: =B12/SUM($B$10:$B$13) -> 0.05 | D12: =C12*$H$9 -> 0.25 | E12: =1/D12 -> 4
A13: Alt Art | B13: 1 | C13: =B13/SUM($B$10:$B$13) -> 0.01 | D13: =C13*$H$9 -> 0.05 | E13: =1/D13 -> 20
A15: Pack layout: 1 Rogue card + 4 playing cards. Each card rolls rarity, effect and art tier independently.
A16: Legendary cards per pack | D16: =C5*$H$9 -> 0.33333333

Sheet Crafting
A1: Rarity | B1: Dismantle (materials) | C1: Craft cost (materials) | D1: Dismantles per craft
A2: Common | B2: 5 | C2: 40 | D2: =C2/B2 -> 8
A3: Rare | B3: 20 | C3: 100 | D3: =C3/B3 -> 5
A4: Epic | B4: 50 | C4: 400 | D4: =C4/B4 -> 8
A5: Legendary | B5: 200 | C5: 1600 | D5: =C5/B5 -> 8
A7: Art tier (dismantle only) | B7: Dismantle multiplier
A8: Default | B8: 1
A9: Holo | B9: 2
A10: Full Art | B10: 4
A11: Alt Art | B11: 8
A13: Crafted cards always get the Default art. Higher art tiers only come from packs, events and art-upgrade tokens, which keeps packs relevant.

Sheet Collection Sim
A1: Monte Carlo simulation (Python, 300 runs per profile). Static output – does not recalculate.
A2: Effects = all 61 effect variants owned (35 card + 26 Rogue). Artworks = all 312 artworks owned (52 playing cards x 4 + 26 Rogue x 4).
A4: Profile | B4: Packs/month | C4: Month 1 effects | D4: Month 2 effects | E4: Month 3 effects | F4: Month 4 effects | G4: Month 5 effects | H4: Month 6 effects | I4: Month 1 artworks | J4: Month 2 artworks | K4: Month 3 artworks | L4: Month 4 artworks | M4: Month 5 artworks | N4: Month 6 artworks
A5: Casual | B5: 14.9 | C5: 0.53 | D5: 0.7 | E5: 0.79 | F5: 0.84 | G5: 0.87 | H5: 0.89 | I5: 0.16 | J5: 0.26 | K5: 0.32 | L5: 0.36 | M5: 0.4 | N5: 0.43
A6: Regular | B6: 30.8 | C6: 0.71 | D6: 0.84 | E6: 0.9 | F6: 0.93 | G6: 0.95 | H6: 0.96 | I6: 0.26 | J6: 0.37 | K6: 0.43 | L6: 0.48 | M6: 0.52 | N6: 0.56
A7: Engaged | B7: 48.9 | C7: 0.8 | D7: 0.9 | E7: 0.94 | F7: 0.96 | G7: 0.97 | H7: 0.98 | I7: 0.33 | J7: 0.44 | K7: 0.52 | L7: 0.57 | M7: 0.61 | N7: 0.64
A8: Hardcore | B8: 55.4 | C8: 0.83 | D8: 0.92 | E8: 0.95 | F8: 0.97 | G8: 0.98 | H8: 0.99 | I8: 0.35 | J8: 0.46 | K8: 0.54 | L8: 0.59 | M8: 0.63 | N8: 0.66
A9: Engaged + premium pass + Daily Pack Pass | B9: 90.9 | C9: 0.9 | D9: 0.96 | E9: 0.98 | F9: 0.99 | G9: 0.99 | H9: 1 | I9: 0.43 | J9: 0.55 | K9: 0.62 | L9: 0.67 | M9: 0.71 | N9: 0.74
